<annotation>
  <folder>VOC2012</folder>
  <filename>455410964.jpg</filename>
  <source>
    <database>The VOC2007 Database</database>
    <annotation>PASCAL VOC2007</annotation>
  </source>
  <size>
    <width>103</width>
    <height>229</height>
    <depth>3</depth>
  </size>
  <segmented>1</segmented>
  <object>
    <name>parkingspot</name>
    <pose>Frontal</pose>
    <truncated>0</truncated>
    <difficult>0</difficult>
    <bndbox>
      <xmin>41</xmin>
      <ymin>34</ymin>
      <xmax>67</xmax>
      <ymax>80</ymax>
    </bndbox>
  </object>
  <object>
    <name>parkingspot</name>
    <pose>Frontal</pose>
    <truncated>0</truncated>
    <difficult>0</difficult>
    <bndbox>
      <xmin>18</xmin>
      <ymin>91</ymin>
      <xmax>55</xmax>
      <ymax>182</ymax>
    </bndbox>
  </object>
  <object>
    <name>parkingspot</name>
    <pose>Frontal</pose>
    <truncated>0</truncated>
    <difficult>0</difficult>
    <bndbox>
      <xmin>49</xmin>
      <ymin>61</ymin>
      <xmax>88</xmax>
      <ymax>188</ymax>
    </bndbox>
  </object>
  <object>
    <name>parkingspot</name>
    <pose>Frontal</pose>
    <truncated>0</truncated>
    <difficult>0</difficult>
    <bndbox>
      <xmin>86</xmin>
      <ymin>43</ymin>
      <xmax>100</xmax>
      <ymax>55</ymax>
    </bndbox>
  </object>
</annotation>
