<annotation>
  <folder>VOC2012</folder>
  <filename>495926981.jpg</filename>
  <source>
    <database>The VOC2007 Database</database>
    <annotation>PASCAL VOC2007</annotation>
  </source>
  <size>
    <width>210</width>
    <height>162</height>
    <depth>3</depth>
  </size>
  <segmented>1</segmented>
  <object>
    <name>parkingspot</name>
    <pose>Frontal</pose>
    <truncated>0</truncated>
    <difficult>0</difficult>
    <bndbox>
      <xmin>30</xmin>
      <ymin>2</ymin>
      <xmax>49</xmax>
      <ymax>22</ymax>
    </bndbox>
  </object>
  <object>
    <name>parkingspot</name>
    <pose>Frontal</pose>
    <truncated>0</truncated>
    <difficult>0</difficult>
    <bndbox>
      <xmin>88</xmin>
      <ymin>106</ymin>
      <xmax>104</xmax>
      <ymax>125</ymax>
    </bndbox>
  </object>
  <object>
    <name>parkingspot</name>
    <pose>Frontal</pose>
    <truncated>0</truncated>
    <difficult>0</difficult>
    <bndbox>
      <xmin>55</xmin>
      <ymin>62</ymin>
      <xmax>75</xmax>
      <ymax>122</ymax>
    </bndbox>
  </object>
  <object>
    <name>parkingspot</name>
    <pose>Frontal</pose>
    <truncated>0</truncated>
    <difficult>0</difficult>
    <bndbox>
      <xmin>132</xmin>
      <ymin>108</ymin>
      <xmax>210</xmax>
      <ymax>128</ymax>
    </bndbox>
  </object>
  <object>
    <name>parkingspot</name>
    <pose>Frontal</pose>
    <truncated>0</truncated>
    <difficult>0</difficult>
    <bndbox>
      <xmin>54</xmin>
      <ymin>38</ymin>
      <xmax>70</xmax>
      <ymax>47</ymax>
    </bndbox>
  </object>
  <object>
    <name>parkingspot</name>
    <pose>Frontal</pose>
    <truncated>0</truncated>
    <difficult>0</difficult>
    <bndbox>
      <xmin>52</xmin>
      <ymin>52</ymin>
      <xmax>69</xmax>
      <ymax>62</ymax>
    </bndbox>
  </object>
  <object>
    <name>parkingspot</name>
    <pose>Frontal</pose>
    <truncated>0</truncated>
    <difficult>0</difficult>
    <bndbox>
      <xmin>39</xmin>
      <ymin>60</ymin>
      <xmax>59</xmax>
      <ymax>120</ymax>
    </bndbox>
  </object>
  <object>
    <name>parkingspot</name>
    <pose>Frontal</pose>
    <truncated>0</truncated>
    <difficult>0</difficult>
    <bndbox>
      <xmin>3</xmin>
      <ymin>127</ymin>
      <xmax>102</xmax>
      <ymax>158</ymax>
    </bndbox>
  </object>
  <object>
    <name>parkingspot</name>
    <pose>Frontal</pose>
    <truncated>0</truncated>
    <difficult>0</difficult>
    <bndbox>
      <xmin>106</xmin>
      <ymin>138</ymin>
      <xmax>193</xmax>
      <ymax>160</ymax>
    </bndbox>
  </object>
</annotation>
