<annotation>
  <folder>VOC2012</folder>
  <filename>224656352.jpg</filename>
  <source>
    <database>The VOC2007 Database</database>
    <annotation>PASCAL VOC2007</annotation>
  </source>
  <size>
    <width>375</width>
    <height>303</height>
    <depth>3</depth>
  </size>
  <segmented>1</segmented>
  <object>
    <name>parkingspot</name>
    <pose>Frontal</pose>
    <truncated>0</truncated>
    <difficult>0</difficult>
    <bndbox>
      <xmin>23</xmin>
      <ymin>12</ymin>
      <xmax>361</xmax>
      <ymax>106</ymax>
    </bndbox>
  </object>
  <object>
    <name>parkingspot</name>
    <pose>Frontal</pose>
    <truncated>0</truncated>
    <difficult>0</difficult>
    <bndbox>
      <xmin>11</xmin>
      <ymin>102</ymin>
      <xmax>84</xmax>
      <ymax>253</ymax>
    </bndbox>
  </object>
  <object>
    <name>parkingspot</name>
    <pose>Frontal</pose>
    <truncated>0</truncated>
    <difficult>0</difficult>
    <bndbox>
      <xmin>28</xmin>
      <ymin>252</ymin>
      <xmax>87</xmax>
      <ymax>298</ymax>
    </bndbox>
  </object>
</annotation>
