<annotation>
  <folder>VOC2012</folder>
  <filename>206212196.jpg</filename>
  <source>
    <database>The VOC2007 Database</database>
    <annotation>PASCAL VOC2007</annotation>
  </source>
  <size>
    <width>192</width>
    <height>210</height>
    <depth>3</depth>
  </size>
  <segmented>1</segmented>
  <object>
    <name>parkingspot</name>
    <pose>Frontal</pose>
    <truncated>0</truncated>
    <difficult>0</difficult>
    <bndbox>
      <xmin>143</xmin>
      <ymin>140</ymin>
      <xmax>192</xmax>
      <ymax>189</ymax>
    </bndbox>
  </object>
  <object>
    <name>parkingspot</name>
    <pose>Frontal</pose>
    <truncated>0</truncated>
    <difficult>0</difficult>
    <bndbox>
      <xmin>121</xmin>
      <ymin>109</ymin>
      <xmax>171</xmax>
      <ymax>157</ymax>
    </bndbox>
  </object>
  <object>
    <name>parkingspot</name>
    <pose>Frontal</pose>
    <truncated>0</truncated>
    <difficult>0</difficult>
    <bndbox>
      <xmin>99</xmin>
      <ymin>75</ymin>
      <xmax>149</xmax>
      <ymax>125</ymax>
    </bndbox>
  </object>
  <object>
    <name>parkingspot</name>
    <pose>Frontal</pose>
    <truncated>0</truncated>
    <difficult>0</difficult>
    <bndbox>
      <xmin>77</xmin>
      <ymin>44</ymin>
      <xmax>126</xmax>
      <ymax>91</ymax>
    </bndbox>
  </object>
  <object>
    <name>parkingspot</name>
    <pose>Frontal</pose>
    <truncated>0</truncated>
    <difficult>0</difficult>
    <bndbox>
      <xmin>57</xmin>
      <ymin>19</ymin>
      <xmax>103</xmax>
      <ymax>59</ymax>
    </bndbox>
  </object>
  <object>
    <name>parkingspot</name>
    <pose>Frontal</pose>
    <truncated>0</truncated>
    <difficult>0</difficult>
    <bndbox>
      <xmin>44</xmin>
      <ymin>1</ymin>
      <xmax>85</xmax>
      <ymax>34</ymax>
    </bndbox>
  </object>
  <object>
    <name>parkingspot</name>
    <pose>Frontal</pose>
    <truncated>0</truncated>
    <difficult>0</difficult>
    <bndbox>
      <xmin>59</xmin>
      <ymin>152</ymin>
      <xmax>105</xmax>
      <ymax>199</ymax>
    </bndbox>
  </object>
  <object>
    <name>parkingspot</name>
    <pose>Frontal</pose>
    <truncated>0</truncated>
    <difficult>0</difficult>
    <bndbox>
      <xmin>35</xmin>
      <ymin>120</ymin>
      <xmax>82</xmax>
      <ymax>168</ymax>
    </bndbox>
  </object>
  <object>
    <name>parkingspot</name>
    <pose>Frontal</pose>
    <truncated>0</truncated>
    <difficult>0</difficult>
    <bndbox>
      <xmin>13</xmin>
      <ymin>86</ymin>
      <xmax>59</xmax>
      <ymax>135</ymax>
    </bndbox>
  </object>
  <object>
    <name>parkingspot</name>
    <pose>Frontal</pose>
    <truncated>0</truncated>
    <difficult>0</difficult>
    <bndbox>
      <xmin>0</xmin>
      <ymin>60</ymin>
      <xmax>31</xmax>
      <ymax>96</ymax>
    </bndbox>
  </object>
</annotation>
