<annotation>
  <folder>VOC2012</folder>
  <filename>33583159.jpg</filename>
  <source>
    <database>The VOC2007 Database</database>
    <annotation>PASCAL VOC2007</annotation>
  </source>
  <size>
    <width>356</width>
    <height>452</height>
    <depth>3</depth>
  </size>
  <segmented>1</segmented>
  <object>
    <name>parkingspot</name>
    <pose>Frontal</pose>
    <truncated>0</truncated>
    <difficult>0</difficult>
    <bndbox>
      <xmin>31</xmin>
      <ymin>40</ymin>
      <xmax>77</xmax>
      <ymax>267</ymax>
    </bndbox>
  </object>
  <object>
    <name>parkingspot</name>
    <pose>Frontal</pose>
    <truncated>0</truncated>
    <difficult>0</difficult>
    <bndbox>
      <xmin>76</xmin>
      <ymin>10</ymin>
      <xmax>163</xmax>
      <ymax>73</ymax>
    </bndbox>
  </object>
  <object>
    <name>parkingspot</name>
    <pose>Frontal</pose>
    <truncated>0</truncated>
    <difficult>0</difficult>
    <bndbox>
      <xmin>187</xmin>
      <ymin>57</ymin>
      <xmax>223</xmax>
      <ymax>129</ymax>
    </bndbox>
  </object>
  <object>
    <name>parkingspot</name>
    <pose>Frontal</pose>
    <truncated>0</truncated>
    <difficult>0</difficult>
    <bndbox>
      <xmin>264</xmin>
      <ymin>160</ymin>
      <xmax>302</xmax>
      <ymax>267</ymax>
    </bndbox>
  </object>
  <object>
    <name>parkingspot</name>
    <pose>Frontal</pose>
    <truncated>0</truncated>
    <difficult>0</difficult>
    <bndbox>
      <xmin>62</xmin>
      <ymin>379</ymin>
      <xmax>108</xmax>
      <ymax>415</ymax>
    </bndbox>
  </object>
  <object>
    <name>parkingspot</name>
    <pose>Frontal</pose>
    <truncated>0</truncated>
    <difficult>0</difficult>
    <bndbox>
      <xmin>119</xmin>
      <ymin>383</ymin>
      <xmax>142</xmax>
      <ymax>417</ymax>
    </bndbox>
  </object>
  <object>
    <name>parkingspot</name>
    <pose>Frontal</pose>
    <truncated>0</truncated>
    <difficult>0</difficult>
    <bndbox>
      <xmin>153</xmin>
      <ymin>385</ymin>
      <xmax>259</xmax>
      <ymax>424</ymax>
    </bndbox>
  </object>
</annotation>
